{"gtabs":[{"panes":[{"ptabs":[{"history":[{"dir":"/home/panos21/Downloads/Parks and Recreation S01-S07 ","file":"Parks and Recreation S02 (360p re-blurip)","relpos":1,"ts":1609887597},{"dir":"/home/panos21/Downloads/Parks and Recreation S01-S07 /Parks and Recreation S02 (360p re-blurip)","file":"..","relpos":0,"ts":1609887597},{"dir":"/home/panos21/Downloads/Parks and Recreation S01-S07 ","file":"..","relpos":0,"ts":1609887597},{"dir":"/home/panos21/Downloads","file":"CSI NY","relpos":9,"ts":1609887597},{"dir":"/home/panos21/Downloads/CSI NY","file":"..","relpos":0,"ts":1609887597},{"dir":"/home/panos21/Downloads","file":"CSI NY","relpos":9,"ts":1609887597},{"dir":"/home/panos21","file":"Downloads","relpos":14,"ts":1609887597},{"dir":"/home/panos21/Downloads","file":"CSI NY","relpos":9,"ts":1609887597},{"dir":"/home/panos21","file":"Downloads","relpos":14,"ts":1609887597},{"dir":"/home/panos21/Downloads","file":"Parks and Recreation S01-S07 ","relpos":29,"ts":1609887597},{"dir":"/home/panos21/Downloads/Parks and Recreation S01-S07 ","file":"Parks and Recreation S02 (360p re-blurip)","relpos":1,"ts":1609887597},{"dir":"/home/panos21/Downloads/Parks and Recreation S01-S07 /Parks and Recreation S02 (360p re-blurip)","file":"..","relpos":0,"ts":1609887597},{"dir":"/home/panos21/Downloads/Parks and Recreation S01-S07 ","file":"..","relpos":0,"ts":1609887597},{"dir":"/home/panos21/Downloads","file":"CSI NY","relpos":9,"ts":1609887597},{"dir":"/home/panos21/Downloads/CSI NY","file":"..","relpos":0,"ts":1609887597},{"dir":"/home/panos21/Downloads","file":"CSI NY","relpos":9,"ts":1609887597},{"dir":"/home/panos21","file":"Downloads","relpos":14,"ts":1609887597},{"dir":"/home/panos21/Downloads","file":"CSI NY","relpos":9,"ts":1609887597},{"dir":"/home/panos21","file":"Downloads","relpos":14,"ts":1609887597},{"dir":"/home/panos21/Downloads","file":"..","relpos":0,"ts":1609887597},{"dir":"/home/panos21","file":"..","relpos":0,"ts":1609887853},{"dir":"/home","file":"..","relpos":0,"ts":1609888271},{"dir":"/","file":"bin","relpos":0,"ts":1609888389},{"dir":"/bin","file":"..","relpos":0,"ts":1609888634},{"dir":"/","file":"bin","relpos":0,"ts":1609888634},{"dir":"/bin","file":"..","relpos":0,"ts":1609888634},{"dir":"/","file":"home","relpos":4,"ts":1609888634},{"dir":"/home","file":"panos21","relpos":1,"ts":1609888634},{"dir":"/home/panos21","file":"Downloads","relpos":14,"ts":1609888634},{"dir":"/bin","file":"..","relpos":0,"ts":1609888634},{"dir":"/","file":"bin","relpos":0,"ts":1609888634},{"dir":"/bin","file":"..","relpos":0,"ts":1609888634},{"dir":"/","file":"home","relpos":4,"ts":1609888634},{"dir":"/home","file":"panos21","relpos":1,"ts":1609888634},{"dir":"/home/panos21","file":"Downloads","relpos":14,"ts":1609888634},{"dir":"/home/panos21/Downloads","file":"The Americans S01-S06","relpos":34,"ts":1609889482},{"dir":"/home/panos21/Downloads/The Americans S01-S06","file":"The Americans S03","relpos":1,"ts":1609889482},{"dir":"/home/panos21/Downloads/The Americans S01-S06/The Americans S03","file":"The Americans S03E02.mp4","relpos":1,"ts":1609889482},{"dir":"/home/panos21/Downloads","file":"The Americans S01-S06","relpos":34,"ts":1609889482},{"dir":"/home/panos21/Downloads/The Americans S01-S06","file":"The Americans S03","relpos":1,"ts":1609889482},{"dir":"/home/panos21/Downloads/The Americans S01-S06/The Americans S03","file":"The Americans S03E02.mp4","relpos":1,"ts":1609889482},{"dir":"/home/panos21/Downloads/The Americans S01-S06","file":"The Americans S03","relpos":1,"ts":1609893286},{"dir":"/home/panos21/Downloads","file":"The Americans S01-S06","relpos":34,"ts":1609893286},{"dir":"/home/panos21/Downloads/The Americans S01-S06","file":"The Americans S03","relpos":1,"ts":1609893286},{"dir":"/home/panos21/Downloads","file":"The Americans S01-S06","relpos":34,"ts":1609893286},{"dir":"/home/panos21/Downloads/The Americans S01-S06","file":"The Americans S03","relpos":0,"ts":1609893360},{"dir":"/home/panos21/Downloads","file":"The Americans S01-S06","relpos":34,"ts":1609893360},{"dir":"/home/panos21","file":"Downloads","relpos":13,"ts":1609893360},{"dir":"/home/panos21/Downloads","file":"Will & Grace S09-S11","relpos":40,"ts":1609893360},{"dir":"/home/panos21/Downloads/Will & Grace S09-S11","file":"Will & Grace S09","relpos":0,"ts":1609893360},{"dir":"/home/panos21/Downloads/Will & Grace S09-S11/Will & Grace S09","file":"Will & Grace S09E01 11 Years Later.mp4","relpos":0,"ts":1609893360},{"dir":"/home/panos21/Downloads/Will & Grace S09-S11","file":"Will & Grace S09","relpos":0,"ts":1609893360},{"dir":"/home/panos21/Downloads","file":"Will & Grace S09-S11","relpos":40,"ts":1609893360},{"dir":"/home/panos21","file":"Downloads","relpos":13,"ts":1609893360},{"dir":"/home","file":"panos21","relpos":0,"ts":1609893360},{"dir":"/","file":"home","relpos":4,"ts":1609893360},{"dir":"/home","file":"panos21","relpos":0,"ts":1609893360},{"dir":"/home/panos21","file":".cache","relpos":0,"ts":1609893360},{"dir":"/home/panos21/Downloads/The Americans S01-S06","file":"The Americans S03","relpos":0,"ts":1609893360},{"dir":"/home/panos21/Downloads","file":"The Americans S01-S06","relpos":34,"ts":1609893360},{"dir":"/home/panos21","file":"Downloads","relpos":13,"ts":1609893360},{"dir":"/home/panos21/Downloads","file":"Will & Grace S09-S11","relpos":40,"ts":1609893360},{"dir":"/home/panos21/Downloads/Will & Grace S09-S11","file":"Will & Grace S09","relpos":0,"ts":1609893360},{"dir":"/home/panos21/Downloads/Will & Grace S09-S11/Will & Grace S09","file":"Will & Grace S09E01 11 Years Later.mp4","relpos":0,"ts":1609893360},{"dir":"/home/panos21/Downloads/Will & Grace S09-S11","file":"Will & Grace S09","relpos":0,"ts":1609893360},{"dir":"/home/panos21/Downloads","file":"Will & Grace S09-S11","relpos":40,"ts":1609893360},{"dir":"/home/panos21","file":"Downloads","relpos":13,"ts":1609893360},{"dir":"/home","file":"panos21","relpos":0,"ts":1609893360},{"dir":"/","file":"home","relpos":4,"ts":1609893360},{"dir":"/home","file":"panos21","relpos":0,"ts":1609893360},{"dir":"/home/panos21","file":".cache","relpos":0,"ts":1609893360},{"dir":"/home","file":"panos21","relpos":0,"ts":1609893460},{"dir":"/","file":"home","relpos":4,"ts":1609893460},{"dir":"/home","file":"panos21","relpos":0,"ts":1609893460},{"dir":"/home/panos21","file":".config","relpos":1,"ts":1609893460},{"dir":"/home","file":"panos21","relpos":0,"ts":1609893460},{"dir":"/","file":"home","relpos":4,"ts":1609893460},{"dir":"/home","file":"panos21","relpos":0,"ts":1609893460},{"dir":"/home/panos21","file":".config","relpos":1,"ts":1609893460},{"dir":"/home/panos21/.config","file":"dconf","relpos":0,"ts":1609893784},{"dir":"/home/panos21","file":".config","relpos":1,"ts":1609893784},{"dir":"/home/panos21/.config","file":"dconf","relpos":0,"ts":1609893784},{"dir":"/home/panos21","file":".config","relpos":1,"ts":1609893784},{"dir":"/home/panos21/.config","file":"dconf","relpos":0,"ts":1609893948},{"dir":"/home/panos21","file":"Downloads","relpos":13,"ts":1609893948},{"dir":"/home/panos21/.config","file":"dconf","relpos":0,"ts":1609893948},{"dir":"/home/panos21","file":"Downloads","relpos":13,"ts":1609893948},{"dir":"/home/panos21/Downloads","file":"Will & Grace S09-S11","relpos":40,"ts":1609894322},{"dir":"/home/panos21/Downloads/Will & Grace S09-S11","file":"Will & Grace S09","relpos":0,"ts":1609894322},{"dir":"/home/panos21/Downloads/Will & Grace S09-S11/Will & Grace S09","file":"Will & Grace S09E01 11 Years Later.mp4","relpos":0,"ts":1609894322},{"dir":"/home/panos21/Downloads","file":"Will & Grace S09-S11","relpos":40,"ts":1609894322},{"dir":"/home/panos21/Downloads/Will & Grace S09-S11","file":"Will & Grace S09","relpos":0,"ts":1609894322},{"dir":"/home/panos21/Downloads/Will & Grace S09-S11/Will & Grace S09","file":"Will & Grace S09E01 11 Years Later.mp4","relpos":0,"ts":1609894322},{"dir":"/home/panos21/Downloads/Will & Grace S09-S11","file":"Will & Grace S09","relpos":0,"ts":1609894803},{"dir":"/home/panos21/Downloads","file":"Cobra Kai S03","relpos":13,"ts":1609894803},{"dir":"/home/panos21/Downloads/Cobra Kai S03","file":"Cobra.Kai.S03E07.720p.WEBRip.x264-GalaxyTV.mkv","relpos":0,"ts":1609894803},{"dir":"/home/panos21/Downloads/Will & Grace S09-S11","file":"Will & Grace S09","relpos":0,"ts":1609894803},{"dir":"/home/panos21/Downloads","file":"Cobra Kai S03","relpos":13,"ts":1609894803},{"dir":"/home/panos21/Downloads/Cobra Kai S03","file":"Cobra.Kai.S03E07.720p.WEBRip.x264-GalaxyTV.mkv","relpos":0,"ts":1609894803},{"dir":"/home/panos21/Downloads","file":"Cobra Kai S03","relpos":13,"ts":1609894942}],"filters":{"invert":true,"dot":false,"manual":"","auto":""},"last-location":"/home/panos21/Downloads","sorting":[2],"preview":false}]},{"ptabs":[{"history":[{"dir":"/home/panos21","file":".zshrc","relpos":29,"ts":1602783336},{"dir":"/home","file":"panos21","relpos":0,"ts":1609894295},{"dir":"/","file":"home","relpos":4,"ts":1609894295},{"dir":"/home","file":"panos21","relpos":0,"ts":1609894295},{"dir":"/home/panos21","file":"dotfiles","relpos":18,"ts":1609894295},{"dir":"/home","file":"panos21","relpos":0,"ts":1609894295},{"dir":"/","file":"home","relpos":4,"ts":1609894295},{"dir":"/home","file":"panos21","relpos":0,"ts":1609894295},{"dir":"/home/panos21","file":"dotfiles","relpos":18,"ts":1609894295},{"dir":"/home","file":"panos21","relpos":0,"ts":1609894322},{"dir":"/home/panos21","file":"dotfiles","relpos":18,"ts":1609894322},{"dir":"/home","file":"panos21","relpos":0,"ts":1609894322},{"dir":"/home/panos21","file":"dotfiles","relpos":18,"ts":1609894322}],"filters":{"invert":true,"dot":false,"manual":"","auto":""},"last-location":"/home/panos21","sorting":[2],"preview":false}]}],"active-pane":0,"preview":false,"splitter":{"pos":-1,"ratio":0.5,"orientation":"v","expanded":false}}],"marks":{"F":{"dir":"/home/panos21/.vifm","file":"..","ts":1609891908},"H":{"dir":"/home/panos21/","file":"..","ts":1602783057},"V":{"dir":"/home/panos21/Videos","file":"..","ts":1609891908},"b":{"dir":"/usr/local/bin/","file":"..","ts":1609893326},"d":{"dir":"/home/panos21/Downloads","file":"..","ts":1609891908},"f":{"dir":"/home/panos21/docs","file":"..","ts":1609894078},"h":{"dir":"/home/panos21/","file":"..","ts":1602783057},"i":{"dir":"/home/panos21/img","file":"..","ts":1609891908},"m":{"dir":"/home/panos21","file":"cache","ts":1609894090},"p":{"dir":"/home/panos21/prog","file":"..","ts":1609891908},"r":{"dir":"/","file":"..","ts":1609891908},"t":{"dir":"/home/panos21/.local/share/vifm/Trash","file":"..","ts":1609891908},"v":{"dir":"/home/panos21/.vim","file":"..","ts":1609891908},"z":{"dir":"/home/panos21/.config/vifm","file":"..","ts":1602783057}},"cmd-hist":[{"text":"wq","ts":1602783336},{"text":"open","ts":1609891548},{"text":"d","ts":1609893948},{"text":"b","ts":1609893948},{"text":"autocmd","ts":1609893948},{"text":"Q","ts":1609894295},{"text":"!q","ts":1609895518},{"text":"q","ts":1609895518}],"regs":{},"dir-stack":[],"use-term-multiplexer":false,"color-scheme":"dracula"}